woc/objects.py
woc/get_values.py
woc/utils.py
woc/local.pxd
woc/tch.pyx
woc/verify.py
woc/remote.py
woc/tch.pxd
woc/wocprofile.default.json
woc/local.pyx
woc/local.cpython-38-x86_64-linux-gnu.so
woc/show_content.py
woc/tch.cpython-38-x86_64-linux-gnu.so
woc/tch.pyi
woc/__init__.py
woc/local.pyi
woc/detect.py
woc/base.py
python_woc-0.4.0.dist-info/LICENSE
python_woc-0.4.0.dist-info/WHEEL
python_woc-0.4.0.dist-info/METADATA
python_woc-0.4.0.dist-info/RECORD
python_woc.libs/libbz2-a273e504.so.1.0.6
