Metadata-Version: 2.1
Name: python-woc
Version: 0.4.0
Summary: Python interface for World of Code
License: GPL-3.0
Author: Runzhi He
Author-email: rzhe@pku.edu.cn
Requires-Python: >=3.8,<4.0
Classifier: License :: OSI Approved :: GNU General Public License v3 (GPLv3)
Classifier: Programming Language :: Python :: 3
Classifier: Programming Language :: Python :: 3.8
Classifier: Programming Language :: Python :: 3.9
Classifier: Programming Language :: Python :: 3.10
Classifier: Programming Language :: Python :: 3.11
Classifier: Programming Language :: Python :: 3.12
Classifier: Programming Language :: Python :: 3.13
Requires-Dist: chardet (>=5.2.0,<6.0.0)
Requires-Dist: httpx (>=0.28.1,<0.29.0)
Requires-Dist: python-lzf (>=0.2.4,<0.3.0)
Requires-Dist: rapidgzip (>=0.14.3,<0.15.0)
Requires-Dist: tqdm (>=4.65.0,<5.0.0)
